gcmark/__init__.py
gcmark/cli.py
gcmark/god_key_hasher.py
gcmark/utils.py
gcmark_vault-1.0.4.dist-info/LICENSE
gcmark_vault-1.0.4.dist-info/METADATA
gcmark_vault-1.0.4.dist-info/WHEEL
gcmark_vault-1.0.4.dist-info/entry_points.txt
gcmark_vault-1.0.4.dist-info/top_level.txt
gcmark_vault-1.0.4.dist-info/RECORD
